airtable_caching/__init__.py
airtable_caching-0.0.5.dist-info/METADATA
airtable_caching-0.0.5.dist-info/WHEEL
airtable_caching-0.0.5.dist-info/top_level.txt
airtable_caching-0.0.5.dist-info/RECORD
