Metadata-Version: 2.1
Name: airtable-caching
Version: 0.0.5
Summary: Utility for caching api responses from the airtable-python-wrapper
Home-page: https://github.com/rmountjoy92/AirtableCaching
Author: rmountjoy
Author-email: ross.mountjoy@gmail.com
License: UNKNOWN
Platform: UNKNOWN
Classifier: Programming Language :: Python :: 3
Classifier: License :: OSI Approved :: MIT License
Classifier: Operating System :: OS Independent
Requires-Python: >=3.6
Requires-Dist: airtable-python-wrapper
